cityofboston/__init__.py
cityofboston/arcgis/__init__.py
cityofboston/arcgis/auth.py
cityofboston/arcgis/client.py
cityofboston/sam/__init__.py
cityofboston/sam/client.py
cityofboston/sam/layers.py
cityofboston-0.1.0.dist-info/WHEEL
cityofboston-0.1.0.dist-info/METADATA
cityofboston-0.1.0.dist-info/RECORD
