Metadata-Version: 2.3
Name: cityofboston
Version: 0.1.0
Summary: City of Boston Python utilities for ArcGIS and data management
Keywords: boston,arcgis,gis,sam
Author: City of Boston
Author-email: City of Boston <digital@boston.gov>
License: MIT
Classifier: Development Status :: 3 - Alpha
Classifier: Intended Audience :: Developers
Classifier: Programming Language :: Python :: 3
Classifier: Programming Language :: Python :: 3.10
Classifier: Programming Language :: Python :: 3.11
Classifier: Programming Language :: Python :: 3.12
Requires-Dist: requests>=2.28.0
Requires-Dist: python-dotenv>=0.19.0
Requires-Dist: pytest>=7.0.0 ; extra == 'dev'
Requires-Dist: pytest-cov>=4.0.0 ; extra == 'dev'
Requires-Dist: pytest-mock>=3.10.0 ; extra == 'dev'
Requires-Dist: geopandas>=0.12.0 ; extra == 'geo'
Requires-Dist: shapely>=2.0.0 ; extra == 'geo'
Requires-Python: >=3.10
Project-URL: Bug Tracker, https://github.com/CityOfBoston/cityofboston-python/issues
Project-URL: Documentation, https://github.com/CityOfBoston/cityofboston-python#readme
Project-URL: Homepage, https://github.com/CityOfBoston/cityofboston-python
Project-URL: Organization, https://pypi.org/org/cityofboston/
Project-URL: Source Code, https://github.com/CityOfBoston/cityofboston-python
Provides-Extra: dev
Provides-Extra: geo
